public_address_generator/__init__.py
public_address_generator-1.1.3.dist-info/METADATA
public_address_generator-1.1.3.dist-info/WHEEL
public_address_generator-1.1.3.dist-info/top_level.txt
public_address_generator-1.1.3.dist-info/RECORD
