Metadata-Version: 2.1
Name: public_address_generator
Version: 1.1.3
Summary: Generate public address from mnemonic-phrase or pivate key
Classifier: Development Status :: 3 - Alpha
Classifier: License :: OSI Approved :: MIT License
Classifier: Natural Language :: English
Classifier: Operating System :: OS Independent
Classifier: Programming Language :: Python
Classifier: Programming Language :: Python :: 3.8
Classifier: Programming Language :: Python :: 3.9
Requires-Python: >=3.8
Requires-Dist: blocksmith
Requires-Dist: hdwallet
Requires-Dist: pycryptodomex
Requires-Dist: eth-account
Requires-Dist: erc20-scanner
